<?xml version="1.0" encoding="UTF-8"?>
<jcr:root xmlns:sling="http://sling.apache.org/jcr/sling/1.0" xmlns:cq="http://www.day.com/jcr/cq/1.0" xmlns:jcr="http://www.jcp.org/jcr/1.0" xmlns:nt="http://www.jcp.org/jcr/nt/1.0"
    jcr:primaryType="nt:unstructured"
    jcr:title="Related Article"
    sling:resourceType="cq/gui/components/authoring/dialog">
    <content
        jcr:primaryType="nt:unstructured"
        sling:resourceType="granite/ui/components/coral/foundation/container">
        <items jcr:primaryType="nt:unstructured">
            <headingTitle
                jcr:primaryType="nt:unstructured"
                sling:resourceType="granite/ui/components/coral/foundation/form/textfield"
                fieldLabel="Heading Title"
                name="./headingTitle"/>
            <headingNavigation
                jcr:primaryType="nt:unstructured"
                sling:resourceType="granite/ui/components/coral/foundation/form/pathfield"
                fieldLabel="Heading Navigation"
                rootPath="/content"
                name="./headingNavigation"/>    
            <relatedArticleDetails
                jcr:primaryType="nt:unstructured"
                sling:resourceType="granite/ui/components/coral/foundation/form/multifield"
                composite="{Boolean}true">
                <field
                    jcr:primaryType="nt:unstructured"
                    sling:resourceType="granite/ui/components/coral/foundation/container"
                    name="./relatedArticleDetails">
                    <items jcr:primaryType="nt:unstructured">
                        <levelOneGroup
                            jcr:primaryType="nt:unstructured"
                            sling:resourceType="granite/ui/components/coral/foundation/well">
                            <items jcr:primaryType="nt:unstructured">
                                <imagePath
                                    jcr:primaryType="nt:unstructured"
                                    sling:resourceType="granite/ui/components/coral/foundation/form/pathfield"
                                    fieldLabel="Image Path"
                                    rootPath="/content/dam/vation"
                                    name="./relatedArticleImage"/>
                                <imageTitle
                                    jcr:primaryType="nt:unstructured"
                                    sling:resourceType="granite/ui/components/coral/foundation/form/textfield"
                                    fieldLabel="Image Title"
                                    name="./imageTitle"/>
                                <imageTitleNavigation
                                    jcr:primaryType="nt:unstructured"
                                    sling:resourceType="granite/ui/components/coral/foundation/form/pathfield"
                                    fieldLabel="Image Title Navigation"
                                    rootPath="/content/dam/vation"
                                    name="./imageTitleNavigation"/> 
                            </items>
                        </levelOneGroup>
                    </items>
                </field>
            </relatedArticleDetails>
        </items>
    </content>
</jcr:root>
